[{"id":"112","name":"\u96f7\u514b\u8428\u65afGX","rank":"\u4e2d\u5927\u578bSUV","brandId":"52"}, {"id":"201","name":"\u96f7\u514b\u8428\u65afIS","rank":"\u4e2d\u578b\u8f66","brandId":"52"}, {"id":"261","name":"\u96f7\u514b\u8428\u65afGS","rank":"\u4e2d\u5927\u578b\u8f66","brandId":"52"}, {"id":"332","name":"\u96f7\u514b\u8428\u65afSC","rank":"\u8dd1\u8f66","brandId":"52"}, {"id":"341","name":"\u96f7\u514b\u8428\u65afLS","rank":"\u8c6a\u534e\u8f66","brandId":"52"}, {"id":"351","name":"\u96f7\u514b\u8428\u65afRX","rank":"\u4e2d\u578bSUV","brandId":"52"}, {"id":"352","name":"\u96f7\u514b\u8428\u65afLX","rank":"\u4e2d\u5927\u578bSUV","brandId":"52"}, {"id":"403","name":"\u96f7\u514b\u8428\u65afES","rank":"\u4e2d\u5927\u578b\u8f66","brandId":"52"}, {"id":"697","name":"\u96f7\u514b\u8428\u65afLFA","rank":"\u8dd1\u8f66","brandId":"52"}, {"id":"2063","name":"\u96f7\u514b\u8428\u65afCT","rank":"\u7d27\u51d1\u578b\u8f66","brandId":"52"}, {"id":"3238","name":"\u96f7\u514b\u8428\u65afRC","rank":"\u8dd1\u8f66","brandId":"52"}, {"id":"3442","name":"\u96f7\u514b\u8428\u65afNX","rank":"\u7d27\u51d1\u578b\u8f66","brandId":"52"}]